sliding1d/__init__.py
sliding1d-1.1.0.dist-info/LICENSE
sliding1d-1.1.0.dist-info/METADATA
sliding1d-1.1.0.dist-info/WHEEL
sliding1d-1.1.0.dist-info/top_level.txt
sliding1d-1.1.0.dist-info/RECORD
