Metadata-Version: 2.1
Name: sliding1d
Version: 1.1.0
Summary: 1D sliding window calculation tools
Home-page: https://github.com/gwappa/python-sliding1d
Author: Keisuke Sehara
Author-email: keisuke.sehara@gmail.com
License: MIT
Platform: UNKNOWN
Classifier: Development Status :: 3 - Alpha
Classifier: License :: OSI Approved :: MIT License
Classifier: Programming Language :: Python :: 3
License-File: LICENSE
Requires-Dist: numpy (>=1.0)
Requires-Dist: bottleneck (>=0.6)
